[
  {
    "id": "simple200L",
    "nameKey": "condorSimple200L",
    "descriptionKey": "condorSimple200LDesc",
    "image": "/images/condor-simple-200l.jpg",
    "category": "oil",
    "volume": "200 L"
  },
  {
    "id": "simple20L",
    "nameKey": "condorSimple20L",
    "descriptionKey": "condorSimple20LDesc",
    "image": "/images/condor-simple-20l.jpg",
    "category": "oil",
    "volume": "20 L"
  },
  {
    "id": "powerGasoline200L",
    "nameKey": "condorPowerGasoline200L",
    "descriptionKey": "condorPowerGasoline200LDesc",
    "image": "/images/condor-power-gasoline-200l.jpg",
    "category": "oil",
    "volume": "200 L"
  },
  {
    "id": "powerGasoline20L",
    "nameKey": "condorPowerGasoline20L",
    "descriptionKey": "condorPowerGasoline20LDesc",
    "image": "/images/condor-power-gasoline-20l.jpg",
    "category": "oil",
    "volume": "20 L"
  },
  {
    "id": "diesel200L",
    "nameKey": "condorDiesel200L",
    "descriptionKey": "condorDiesel200LDesc",
    "image": "/images/condor-diesel-200l.jpg",
    "category": "oil",
    "volume": "200 L"
  },
  {
    "id": "diesel20L",
    "nameKey": "condorDiesel20L",
    "descriptionKey": "condorDiesel20LDesc",
    "image": "/images/condor-diesel-20l.jpg",
    "category": "oil",
    "volume": "20 L"
  },
  {
    "id": "diesel10L",
    "nameKey": "condorDiesel10L",
    "descriptionKey": "condorDiesel10LDesc",
    "image": "/images/condor-diesel-10l.jpg",
    "category": "oil",
    "volume": "10 L"
  },
  {
    "id": "powerDiesel200L",
    "nameKey": "condorPowerDiesel200L",
    "descriptionKey": "condorPowerDiesel200LDesc",
    "image": "/images/condor-power-diesel-200l.jpg",
    "category": "oil",
    "volume": "200 L"
  },
  {
    "id": "powerDiesel50L",
    "nameKey": "condorPowerDiesel50L",
    "descriptionKey": "condorPowerDiesel50LDesc",
    "image": "/images/condor-power-diesel-50l.jpg",
    "category": "oil",
    "volume": "50 L"
  },
  {
    "id": "powerDiesel20L",
    "nameKey": "condorPowerDiesel20L",
    "descriptionKey": "condorPowerDiesel20LDesc",
    "image": "/images/condor-power-diesel-20l.jpg",
    "category": "oil",
    "volume": "20 L"
  },
  {
    "id": "powerDiesel10L",
    "nameKey": "condorPowerDiesel10L",
    "descriptionKey": "condorPowerDiesel10LDesc",
    "image": "/images/condor-power-diesel-10l.jpg",
    "category": "oil",
    "volume": "10 L"
  },
  {
    "id": "turboDiesel20L",
    "nameKey": "condorTurboDiesel20L",
    "descriptionKey": "condorTurboDiesel20LDesc",
    "image": "/images/condor-turbo-diesel-20l.jpg",
    "category": "oil",
    "volume": "20 L"
  },
  {
    "id": "hd46_20L",
    "nameKey": "condorHD46_20L",
    "descriptionKey": "condorHD46_20LDesc",
    "image": "/images/condor-hd46-20l.jpg",
    "category": "oil",
    "volume": "20 L"
  },
  {
    "id": "hd68_20L",
    "nameKey": "condorHD68_20L",
    "descriptionKey": "condorHD68_20LDesc",
    "image": "/images/condor-hd68-20l.jpg",
    "category": "oil",
    "volume": "20 L"
  },
  {
    "id": "antifreeze20L",
    "nameKey": "condorUZ20L",
    "descriptionKey": "condorUZ20LDesc",
    "image": "/images/condor-uz-20l.jpg",
    "category": "antifreeze",
    "volume": "20 L"
  },
  {
    "id": "antifreeze10L",
    "nameKey": "condorUZ10L",
    "descriptionKey": "condorUZ10LDesc",
    "image": "/images/condor-uz-10l.jpg",
    "category": "antifreeze",
    "volume": "10 L"
  },
  {
    "id": "antifreeze5L",
    "nameKey": "condorUZ5L",
    "descriptionKey": "condorUZ5LDesc",
    "image": "/images/condor-uz-5l.jpg",
    "category": "antifreeze",
    "volume": "5 L"
  },
  {
    "id": "antifreeze4L",
    "nameKey": "condorUZ4L",
    "descriptionKey": "condorUZ4LDesc",
    "image": "/images/condor-uz-4l.jpg",
    "category": "antifreeze",
    "volume": "4 L"
  },
  {
    "id": "antifreeze3L",
    "nameKey": "condorUZ3L",
    "descriptionKey": "condorUZ3LDesc",
    "image": "/images/condor-uz-3l.jpg",
    "category": "antifreeze",
    "volume": "3 L"
  },
  {
    "id": "antifreezeUZ",
    "nameKey": "condorUZ",
    "descriptionKey": "condorUZDesc",
    "image": "/images/condor-uz.jpg",
    "category": "antifreeze"
  },
  {
    "id": "antifreezeUZDolivka",
    "nameKey": "condorUZDolivka",
    "descriptionKey": "condorUZDolivkaDesc",
    "image": "/images/condor-uz-dolivka.jpg",
    "category": "antifreeze"
  },
  {
    "id": "dot4_455gr",
    "nameKey": "condorDOT4_455gr",
    "descriptionKey": "condorDOT4_455grDesc",
    "image": "/images/condor-dot4-455gr.jpg",
    "category": "dot",
    "volume": "455 gr"
  },
  {
    "id": "dot4_100gr",
    "nameKey": "condorDOT4_100gr",
    "descriptionKey": "condorDOT4_100grDesc",
    "image": "/images/condor-dot4-100gr.jpg",
    "category": "dot",
    "volume": "100 gr"
  },
  {
    "id": "waterLabovoy1L",
    "nameKey": "waterLabovoy1L",
    "descriptionKey": "waterLabovoy1LDesc",
    "image": "/images/water-labovoy-1l.jpg",
    "category": "water",
    "volume": "1 L"
  },
  {
    "id": "waterLabovoy5L",
    "nameKey": "waterLabovoy5L",
    "descriptionKey": "waterLabovoy5LDesc",
    "image": "/images/water-labovoy-5l.jpg",
    "category": "water",
    "volume": "5 L"
  }
]
